optionlab/.gitignore
optionlab/__init__.py
optionlab/black_scholes.py
optionlab/engine.py
optionlab/models.py
optionlab/plot.py
optionlab/support.py
optionlab/utils.py
optionlab-1.5.1.dist-info/LICENSE
optionlab-1.5.1.dist-info/METADATA
optionlab-1.5.1.dist-info/WHEEL
optionlab-1.5.1.dist-info/RECORD
