Metadata-Version: 2.1
Name: optionlab
Version: 1.5.1
Summary: Python library for evaluating options trading strategies
Author: Roberto Gomes, PhD
Author-email: roberto.veiga@ufabc.edu.br
Requires-Python: >=3.10,<4.0
Classifier: Programming Language :: Python :: 3
Classifier: Programming Language :: Python :: 3.10
Classifier: Programming Language :: Python :: 3.11
Requires-Dist: holidays (>=0.44,<0.45)
Requires-Dist: jupyter (>=1.0.0,<2.0.0)
Requires-Dist: matplotlib (>=3.8.3,<4.0.0)
Requires-Dist: pandas (>=2.2.1,<3.0.0)
Requires-Dist: pydantic (>=2.9,<3.0)
Requires-Dist: scipy (>=1.12.0,<2.0.0)
